scripterminator/__init__.py
scripterminator/scripterminator.py
scripterminator-1.0.2.dist-info/LICENSE.txt
scripterminator-1.0.2.dist-info/METADATA
scripterminator-1.0.2.dist-info/WHEEL
scripterminator-1.0.2.dist-info/top_level.txt
scripterminator-1.0.2.dist-info/RECORD
