Metadata-Version: 2.1
Name: scripterminator
Version: 1.0.2
Summary: Useful tool to terminate any Python script just using file path and name
Home-page: https://github.com/shahminrinkey/scripterminator
Author: Shahmin Rahman Rinkey
Author-email: shahminrinkey02@gmail.com
License: MIT
Download-URL: https://pypi.org/project/scripterminator/
Keywords: process,psutil,pid,terminate,system,utility,os
Platform: UNKNOWN
Requires-Dist: psutil
